{
  "video_id": "01_0027",
  "gate_score": 0.9963929057121277,
  "n_segments": 25,
  "segment_scores": [
    0.026535281911492348,
    0.04157558083534241,
    0.19227814674377441,
    0.13837501406669617,
    0.37677380442619324,
    0.5227968692779541,
    0.6320438385009766,
    0.6592637300491333,
    0.8453960418701172,
    0.8189714550971985,
    0.9909707307815552,
    0.9982579946517944,
    0.9999497532844543,
    0.999921977519989,
    0.9998685121536255,
    0.9989992380142212,
    0.9976125955581665,
    0.9804153442382812,
    0.901271641254425,
    0.8925254940986633,
    0.8500306010246277,
    0.5566008687019348,
    0.2127304971218109,
    0.11868585646152496,
    0.01642589084804058
  ],
  "anomalous_segments": [
    {
      "start_snippet": 4,
      "end_snippet": 21,
      "selected_snippets": [
        {
          "snippet_idx": 4,
          "score": 0.37677380442619324
        },
        {
          "snippet_idx": 8,
          "score": 0.8453960418701172
        },
        {
          "snippet_idx": 10,
          "score": 0.9909707307815552
        },
        {
          "snippet_idx": 12,
          "score": 0.9999497532844543
        },
        {
          "snippet_idx": 14,
          "score": 0.9998685121536255
        },
        {
          "snippet_idx": 16,
          "score": 0.9976125955581665
        },
        {
          "snippet_idx": 18,
          "score": 0.901271641254425
        },
        {
          "snippet_idx": 21,
          "score": 0.5566008687019348
        }
      ]
    }
  ],
  "extracted_frames": [
    {
      "snippet_idx": 4,
      "score": 0.37677380442619324,
      "frame_num": 73,
      "file": "snippet_004_frame_0073.jpg"
    },
    {
      "snippet_idx": 8,
      "score": 0.8453960418701172,
      "frame_num": 138,
      "file": "snippet_008_frame_0138.jpg"
    },
    {
      "snippet_idx": 10,
      "score": 0.9909707307815552,
      "frame_num": 171,
      "file": "snippet_010_frame_0171.jpg"
    },
    {
      "snippet_idx": 12,
      "score": 0.9999497532844543,
      "frame_num": 204,
      "file": "snippet_012_frame_0204.jpg"
    },
    {
      "snippet_idx": 14,
      "score": 0.9998685121536255,
      "frame_num": 237,
      "file": "snippet_014_frame_0237.jpg"
    },
    {
      "snippet_idx": 16,
      "score": 0.9976125955581665,
      "frame_num": 269,
      "file": "snippet_016_frame_0269.jpg"
    },
    {
      "snippet_idx": 18,
      "score": 0.901271641254425,
      "frame_num": 302,
      "file": "snippet_018_frame_0302.jpg"
    },
    {
      "snippet_idx": 21,
      "score": 0.5566008687019348,
      "frame_num": 351,
      "file": "snippet_021_frame_0351.jpg"
    }
  ]
}