{
  "video_id": "01_0139",
  "variant": "video_only",
  "human_explanation": "A person in a blue shirt is riding a bicycle in a pedestrian-only area where cycling is not allowed.",
  "segments": [
    {
      "segment_index": 0,
      "ai_explanation": "All frames show pedestrians walking calmly, which is normal activity for the scene.",
      "scores": {
        "correctness": 1,
        "specificity": 1,
        "completeness": 1,
        "fluency": 3,
        "justification": "The AI explanation fails to identify the anomaly of a person riding a bicycle in a pedestrian-only area. It vaguely describes normal pedestrian activity, lacking the required specific details about the event. The explanation is somewhat clear, but it does not address any of the key aspects of the human description."
      }
    }
  ]
}