{
  "video_id": "01_0051",
  "gate_score": 0.9589945673942566,
  "n_segments": 21,
  "segment_scores": [
    0.14533157646656036,
    0.3325191140174866,
    0.36716875433921814,
    0.5586420297622681,
    0.8742920160293579,
    0.9879664778709412,
    0.9962198138237,
    0.9975330233573914,
    0.9925422668457031,
    0.998579204082489,
    0.9959880709648132,
    0.9941478967666626,
    0.9774635434150696,
    0.9828912019729614,
    0.9830695986747742,
    0.8970903754234314,
    0.8344659209251404,
    0.9767562747001648,
    0.9993812441825867,
    0.8800692558288574,
    0.5826486945152283
  ],
  "anomalous_segments": [
    {
      "start": 1,
      "end": 20
    }
  ],
  "extracted_frames": [
    {
      "snippet_idx": 1,
      "score": 0.3325191140174866,
      "frame_num": 24,
      "file": "snippet_001_frame_0024.jpg"
    },
    {
      "snippet_idx": 5,
      "score": 0.9879664778709412,
      "frame_num": 88,
      "file": "snippet_005_frame_0088.jpg"
    },
    {
      "snippet_idx": 7,
      "score": 0.9975330233573914,
      "frame_num": 120,
      "file": "snippet_007_frame_0120.jpg"
    },
    {
      "snippet_idx": 9,
      "score": 0.998579204082489,
      "frame_num": 152,
      "file": "snippet_009_frame_0152.jpg"
    },
    {
      "snippet_idx": 11,
      "score": 0.9941478967666626,
      "frame_num": 184,
      "file": "snippet_011_frame_0184.jpg"
    },
    {
      "snippet_idx": 14,
      "score": 0.9830695986747742,
      "frame_num": 232,
      "file": "snippet_014_frame_0232.jpg"
    },
    {
      "snippet_idx": 18,
      "score": 0.9993812441825867,
      "frame_num": 296,
      "file": "snippet_018_frame_0296.jpg"
    },
    {
      "snippet_idx": 20,
      "score": 0.5826486945152283,
      "frame_num": 328,
      "file": "snippet_020_frame_0328.jpg"
    }
  ]
}