{
  "video_id": "01_0025",
  "gate_score": 0.99985671043396,
  "n_segments": 37,
  "segment_scores": [
    0.19624760746955872,
    0.3284117877483368,
    0.39772599935531616,
    0.4886402189731598,
    0.5362109541893005,
    0.7274342775344849,
    0.993010401725769,
    0.9987580180168152,
    0.9987489581108093,
    0.9896828532218933,
    0.990825355052948,
    0.9997807741165161,
    0.9986323118209839,
    0.9997674226760864,
    0.9999039769172668,
    0.9998987317085266,
    0.999870777130127,
    0.9594268798828125,
    0.8920553922653198,
    0.8101289868354797,
    0.8690387606620789,
    0.8628795742988586,
    0.7845815420150757,
    0.6716103553771973,
    0.5249110460281372,
    0.507763147354126,
    0.5157254934310913,
    0.522477924823761,
    0.5407190918922424,
    0.5798373818397522,
    0.5982471704483032,
    0.5889256000518799,
    0.5048595070838928,
    0.33976706862449646,
    0.0737864077091217,
    0.02302565798163414,
    0.004959306679666042
  ],
  "anomalous_segments": [
    {
      "start_snippet": 1,
      "end_snippet": 33,
      "selected_snippets": [
        {
          "snippet_idx": 1,
          "score": 0.3284117877483368
        },
        {
          "snippet_idx": 7,
          "score": 0.9987580180168152
        },
        {
          "snippet_idx": 9,
          "score": 0.9896828532218933
        },
        {
          "snippet_idx": 11,
          "score": 0.9997807741165161
        },
        {
          "snippet_idx": 14,
          "score": 0.9999039769172668
        },
        {
          "snippet_idx": 16,
          "score": 0.999870777130127
        },
        {
          "snippet_idx": 18,
          "score": 0.8920553922653198
        },
        {
          "snippet_idx": 33,
          "score": 0.33976706862449646
        }
      ]
    }
  ],
  "extracted_frames": [
    {
      "snippet_idx": 1,
      "score": 0.3284117877483368,
      "frame_num": 24,
      "file": "snippet_001_frame_0024.jpg"
    },
    {
      "snippet_idx": 7,
      "score": 0.9987580180168152,
      "frame_num": 121,
      "file": "snippet_007_frame_0121.jpg"
    },
    {
      "snippet_idx": 9,
      "score": 0.9896828532218933,
      "frame_num": 154,
      "file": "snippet_009_frame_0154.jpg"
    },
    {
      "snippet_idx": 11,
      "score": 0.9997807741165161,
      "frame_num": 186,
      "file": "snippet_011_frame_0186.jpg"
    },
    {
      "snippet_idx": 14,
      "score": 0.9999039769172668,
      "frame_num": 235,
      "file": "snippet_014_frame_0235.jpg"
    },
    {
      "snippet_idx": 16,
      "score": 0.999870777130127,
      "frame_num": 267,
      "file": "snippet_016_frame_0267.jpg"
    },
    {
      "snippet_idx": 18,
      "score": 0.8920553922653198,
      "frame_num": 300,
      "file": "snippet_018_frame_0300.jpg"
    },
    {
      "snippet_idx": 33,
      "score": 0.33976706862449646,
      "frame_num": 544,
      "file": "snippet_033_frame_0544.jpg"
    }
  ]
}